mypackage/__init__.py
mypackage/decorators.py
mypackage/descriptors.py
mypackage/generators.py
mypackage/iterators.py
mypackage-grigory3342/__init__.py
mypackage-grigory3342/decorators.py
mypackage-grigory3342/descriptors.py
mypackage-grigory3342/generators.py
mypackage-grigory3342/iterators.py
mypackage3342/__init__.py
mypackage3342/decorators.py
mypackage3342/descriptors.py
mypackage3342/generators.py
mypackage3342/iterators.py
mypackage_grigory3342/__init__.py
mypackage_grigory3342/decorators.py
mypackage_grigory3342/descriptors.py
mypackage_grigory3342/generators.py
mypackage_grigory3342/iterators.py
mypackage3342-0.1.dist-info/METADATA
mypackage3342-0.1.dist-info/WHEEL
mypackage3342-0.1.dist-info/top_level.txt
mypackage3342-0.1.dist-info/RECORD
